twone/__init__.py
twone/container.py
twone-0.5.0.dist-info/LICENSE
twone-0.5.0.dist-info/METADATA
twone-0.5.0.dist-info/WHEEL
twone-0.5.0.dist-info/top_level.txt
twone-0.5.0.dist-info/RECORD
