Metadata-Version: 2.1
Name: twone
Version: 0.5.0
Summary: machine learning library for easily manipulating data
Home-page: https://github.com/sepmein/twone
Author: Spencer Zhang
Author-email: sepmein@hotmail.com
License: MIT
Keywords: tensorflow data-preprocessing machine-learning
Platform: UNKNOWN
Classifier: Development Status :: 3 - Alpha
Classifier: Intended Audience :: Developers
Classifier: Topic :: Scientific/Engineering :: Artificial Intelligence
Classifier: License :: OSI Approved :: MIT License
Classifier: Programming Language :: Python :: 2
Classifier: Programming Language :: Python :: 2.7
Classifier: Programming Language :: Python :: 3
Classifier: Programming Language :: Python :: 3.3
Classifier: Programming Language :: Python :: 3.4
Classifier: Programming Language :: Python :: 3.5
Requires-Dist: numpy
Requires-Dist: pandas
Requires-Dist: sklearn
